CHANGES.rst
LICENSE
MANIFEST.in
README.rst
setup.py
Serializer.egg-info/PKG-INFO
Serializer.egg-info/SOURCES.txt
Serializer.egg-info/dependency_links.txt
Serializer.egg-info/not-zip-safe
Serializer.egg-info/requires.txt
Serializer.egg-info/top_level.txt
docs/Makefile
docs/conf.py
docs/index.rst
docs/make.bat
serializer/__init__.py