Metadata-Version: 1.1
Name: Serializer
Version: 0.1.0
Summary: Easy object serialization. Mimics RoR ActiveRecord serializer.
Home-page: http://github.com/kvesteri/serializer
Author: Konsta Vesterinen
Author-email: konsta.vesterinen@gmail.com
License: BSD
Platform: any
Classifier: Development Status :: 4 - Beta
Classifier: Intended Audience :: Developers
Classifier: License :: OSI Approved :: BSD License
Classifier: Operating System :: OS Independent
Classifier: Programming Language :: Python
Classifier: Topic :: Software Development :: Libraries :: Python Modules
